np_mplchart/__init__.py
np_mplchart/_base.py
np_mplchart/_cursor.py
np_mplchart/_draw.py
np_mplchart/_slider.py
np_mplchart/test.py
np_mplchart/utils.py
np_mplchart-1.3.1.3.dist-info/METADATA
np_mplchart-1.3.1.3.dist-info/WHEEL
np_mplchart-1.3.1.3.dist-info/top_level.txt
np_mplchart-1.3.1.3.dist-info/RECORD
